ccptools/__init__.py
ccptools/_common/__init__.py
ccptools/_common/_decode.py
ccptools/dtu/__init__.py
ccptools/dtu/casting/__init__.py
ccptools/dtu/casting/_any.py
ccptools/dtu/casting/_filetime.py
ccptools/dtu/casting/_instant.py
ccptools/dtu/casting/_string.py
ccptools/dtu/casting/_timestamp.py
ccptools/dtu/formatting/__init__.py
ccptools/dtu/formatting/_delta.py
ccptools/dtu/formatting/_serialize.py
ccptools/dtu/parsers/__init__.py
ccptools/dtu/parsers/_string.py
ccptools/dtu/parsers/_timedelta.py
ccptools/dtu/shortcuts/__init__.py
ccptools/dtu/shortcuts/_aliases.py
ccptools/dtu/shortcuts/_checkers.py
ccptools/dtu/shortcuts/_finders.py
ccptools/dtu/structs/__init__.py
ccptools/dtu/structs/_base.py
ccptools/dtu/structs/_deltasplit.py
ccptools/dtu/structs/_types.py
ccptools/dtu/structs/aliases.py
ccptools/dtu/structs/consts.py
ccptools/legacyapi/__init__.py
ccptools/legacyapi/datetimeutils/__init__.py
ccptools/legacyapi/datetimeutils/_deltasplit.py
ccptools/legacyapi/datetimeutils/_find.py
ccptools/legacyapi/datetimeutils/_timestamp.py
ccptools/legacyapi/typeutils/__init__.py
ccptools/legacyapi/typeutils/bases.py
ccptools/legacyapi/typeutils/casting.py
ccptools/legacyapi/typeutils/comparison.py
ccptools/legacyapi/typeutils/empty.py
ccptools/legacyapi/typeutils/insp.py
ccptools/legacyapi/typeutils/iters.py
ccptools/legacyapi/typeutils/metas.py
ccptools/legacyapi/typeutils/sentience.py
ccptools/legacyapi/typeutils/size.py
ccptools/legacyapi/typeutils/strimp.py
ccptools/legacyapi/typeutils/string.py
ccptools/structs/__init__.py
ccptools/structs/_base.py
ccptools/tpu/__init__.py
ccptools/tpu/casting/__init__.py
ccptools/tpu/casting/_currency.py
ccptools/tpu/casting/_evals.py
ccptools/tpu/casting/_ip.py
ccptools/tpu/casting/_mask.py
ccptools/tpu/casting/_params.py
ccptools/tpu/casting/_serialize.py
ccptools/tpu/comparison/__init__.py
ccptools/tpu/comparison/_mixin.py
ccptools/tpu/insp/__init__.py
ccptools/tpu/insp/_insp_old.py
ccptools/tpu/insp/_typecheck.py
ccptools-1.2.0.dist-info/LICENSE
ccptools-1.2.0.dist-info/METADATA
ccptools-1.2.0.dist-info/WHEEL
ccptools-1.2.0.dist-info/top_level.txt
ccptools-1.2.0.dist-info/RECORD
