Metadata-Version: 2.1
Name: ccptools
Version: 1.2.0
Summary: The CCP Tools team utilities for date and/or time objects and values and messing with types.
Author-email: Thordur Matthiasson <thordurm@ccpgames.com>, John Aldis <johnaldis@ccpgames.com>
License: MIT License
Project-URL: Homepage, https://github.com/ccpgames/ccptools
Project-URL: Documentation, https://github.com/ccpgames/ccptools/blob/main/README.md
Project-URL: Repository, https://github.com/ccpgames/ccptools.git
Project-URL: Issues, https://github.com/ccpgames/ccptools/issues
Project-URL: Changelog, https://github.com/ccpgames/ccptools/blob/main/CHANGELOG.md
Keywords: datetimeutils,datetime,typeutils,type,singleton,date,time,timespan,tools,ccp,utils
Classifier: Development Status :: 5 - Production/Stable
Classifier: License :: OSI Approved :: MIT License
Classifier: Intended Audience :: Developers
Classifier: Programming Language :: Python
Classifier: Programming Language :: Python :: 3
Classifier: Programming Language :: Python :: 3.8
Classifier: Programming Language :: Python :: 3.9
Classifier: Programming Language :: Python :: 3.10
Classifier: Programming Language :: Python :: 3.11
Classifier: Programming Language :: Python :: 3.12
Classifier: Topic :: Software Development
Classifier: Topic :: Software Development :: Libraries
Classifier: Topic :: Software Development :: Libraries :: Python Modules
Classifier: Topic :: Utilities
License-File: LICENSE
